{
  "abstract_role": "retained",
  "abstract_state": "proof/states/retained-state.json",
  "case": "a=1",
  "checks": [
    {
      "abstract": 41,
      "concrete": 41,
      "field": "frontier_pc",
      "passed": true
    },
    {
      "field": "environment.same_suffix",
      "passed": true
    },
    {
      "field": "environment.serialized_execution",
      "passed": true
    },
    {
      "field": "omitted_map_occupancy_recorded",
      "passed": true
    }
  ],
  "concrete_state": "proof/concrete/sigma-a1.json",
  "field_checks": [
    {
      "abstract": 41,
      "concrete": 41,
      "field": "frontier_pc",
      "passed": true,
      "result": "PASS",
      "rule": "frontier-pc-match"
    },
    {
      "field": "environment.same_suffix",
      "passed": true,
      "result": "PASS",
      "rule": "environment-contract"
    },
    {
      "field": "environment.serialized_execution",
      "passed": true,
      "result": "PASS",
      "rule": "environment-contract"
    },
    {
      "field": "omitted_map_occupancy_recorded",
      "passed": true,
      "result": "PASS",
      "rule": "omitted-runtime-component-recorded"
    },
    {
      "field": "frame.frameno",
      "passed": true,
      "result": "PASS",
      "rule": "frame-shape"
    },
    {
      "field": "frame.allocated_stack",
      "passed": true,
      "result": "PASS",
      "rule": "frame-shape"
    },
    {
      "abstract": "NOT_INIT",
      "concrete_kind": "uninitialized",
      "field": "regs.r0.type",
      "passed": true,
      "result": "PASS",
      "rule": "register-type-kind"
    },
    {
      "field": "regs.r0.uninitialized",
      "passed": true,
      "result": "PASS",
      "rule": "not-init"
    },
    {
      "abstract": "NOT_INIT",
      "concrete_kind": "uninitialized",
      "field": "regs.r1.type",
      "passed": true,
      "result": "PASS",
      "rule": "register-type-kind"
    },
    {
      "field": "regs.r1.uninitialized",
      "passed": true,
      "result": "PASS",
      "rule": "not-init"
    },
    {
      "abstract": "NOT_INIT",
      "concrete_kind": "uninitialized",
      "field": "regs.r2.type",
      "passed": true,
      "result": "PASS",
      "rule": "register-type-kind"
    },
    {
      "field": "regs.r2.uninitialized",
      "passed": true,
      "result": "PASS",
      "rule": "not-init"
    },
    {
      "abstract": "NOT_INIT",
      "concrete_kind": "uninitialized",
      "field": "regs.r3.type",
      "passed": true,
      "result": "PASS",
      "rule": "register-type-kind"
    },
    {
      "field": "regs.r3.uninitialized",
      "passed": true,
      "result": "PASS",
      "rule": "not-init"
    },
    {
      "abstract": "NOT_INIT",
      "concrete_kind": "uninitialized",
      "field": "regs.r4.type",
      "passed": true,
      "result": "PASS",
      "rule": "register-type-kind"
    },
    {
      "field": "regs.r4.uninitialized",
      "passed": true,
      "result": "PASS",
      "rule": "not-init"
    },
    {
      "abstract": "NOT_INIT",
      "concrete_kind": "uninitialized",
      "field": "regs.r5.type",
      "passed": true,
      "result": "PASS",
      "rule": "register-type-kind"
    },
    {
      "field": "regs.r5.uninitialized",
      "passed": true,
      "result": "PASS",
      "rule": "not-init"
    },
    {
      "abstract": "NOT_INIT",
      "concrete_kind": "uninitialized",
      "field": "regs.r6.type",
      "passed": true,
      "result": "PASS",
      "rule": "register-type-kind"
    },
    {
      "field": "regs.r6.uninitialized",
      "passed": true,
      "result": "PASS",
      "rule": "not-init"
    },
    {
      "abstract": "NOT_INIT",
      "concrete_kind": "uninitialized",
      "field": "regs.r7.type",
      "passed": true,
      "result": "PASS",
      "rule": "register-type-kind"
    },
    {
      "field": "regs.r7.uninitialized",
      "passed": true,
      "result": "PASS",
      "rule": "not-init"
    },
    {
      "abstract": "NOT_INIT",
      "concrete_kind": "uninitialized",
      "field": "regs.r8.type",
      "passed": true,
      "result": "PASS",
      "rule": "register-type-kind"
    },
    {
      "field": "regs.r8.uninitialized",
      "passed": true,
      "result": "PASS",
      "rule": "not-init"
    },
    {
      "abstract": "NOT_INIT",
      "concrete_kind": "uninitialized",
      "field": "regs.r9.type",
      "passed": true,
      "result": "PASS",
      "rule": "register-type-kind"
    },
    {
      "field": "regs.r9.uninitialized",
      "passed": true,
      "result": "PASS",
      "rule": "not-init"
    },
    {
      "abstract": "PTR_TO_STACK",
      "concrete_kind": "ptr_to_stack",
      "field": "regs.r10.type",
      "passed": true,
      "result": "PASS",
      "rule": "register-type-kind"
    },
    {
      "field": "regs.r10.ptr_kind",
      "passed": true,
      "result": "PASS",
      "rule": "pointer-kind-and-offset"
    },
    {
      "abstract": 0,
      "concrete": 0,
      "field": "regs.r10.offset",
      "passed": true,
      "result": "PASS",
      "rule": "pointer-kind-and-offset"
    },
    {
      "field": "regs.r10.var_off",
      "passed": true,
      "result": "PASS",
      "rule": "ptr-tnum",
      "tnum": {
        "mask": 0,
        "value": 0
      }
    },
    {
      "field": "stack.slot0.initialized",
      "passed": true,
      "result": "PASS",
      "rule": "stack-slot-shape"
    },
    {
      "abstract": [
        0,
        0,
        0,
        0,
        0,
        0,
        0,
        0
      ],
      "field": "stack.slot0.slot_type",
      "passed": true,
      "result": "PASS",
      "rule": "stack-slot-shape"
    },
    {
      "field": "stack.slot1.initialized",
      "passed": true,
      "result": "PASS",
      "rule": "stack-slot-shape"
    },
    {
      "abstract": [
        0,
        0,
        0,
        0,
        0,
        0,
        0,
        0
      ],
      "field": "stack.slot1.slot_type",
      "passed": true,
      "result": "PASS",
      "rule": "stack-slot-shape"
    }
  ],
  "frame": {
    "checks": [
      {
        "field": "frameno",
        "passed": true
      },
      {
        "field": "allocated_stack",
        "passed": true
      }
    ],
    "passed": true,
    "reasons": [],
    "registers": [
      {
        "checks": [
          {
            "abstract": "NOT_INIT",
            "concrete_kind": "uninitialized",
            "field": "type",
            "passed": true
          },
          {
            "field": "uninitialized",
            "passed": true
          }
        ],
        "passed": true,
        "reasons": [],
        "reg": 0,
        "type": "NOT_INIT"
      },
      {
        "checks": [
          {
            "abstract": "NOT_INIT",
            "concrete_kind": "uninitialized",
            "field": "type",
            "passed": true
          },
          {
            "field": "uninitialized",
            "passed": true
          }
        ],
        "passed": true,
        "reasons": [],
        "reg": 1,
        "type": "NOT_INIT"
      },
      {
        "checks": [
          {
            "abstract": "NOT_INIT",
            "concrete_kind": "uninitialized",
            "field": "type",
            "passed": true
          },
          {
            "field": "uninitialized",
            "passed": true
          }
        ],
        "passed": true,
        "reasons": [],
        "reg": 2,
        "type": "NOT_INIT"
      },
      {
        "checks": [
          {
            "abstract": "NOT_INIT",
            "concrete_kind": "uninitialized",
            "field": "type",
            "passed": true
          },
          {
            "field": "uninitialized",
            "passed": true
          }
        ],
        "passed": true,
        "reasons": [],
        "reg": 3,
        "type": "NOT_INIT"
      },
      {
        "checks": [
          {
            "abstract": "NOT_INIT",
            "concrete_kind": "uninitialized",
            "field": "type",
            "passed": true
          },
          {
            "field": "uninitialized",
            "passed": true
          }
        ],
        "passed": true,
        "reasons": [],
        "reg": 4,
        "type": "NOT_INIT"
      },
      {
        "checks": [
          {
            "abstract": "NOT_INIT",
            "concrete_kind": "uninitialized",
            "field": "type",
            "passed": true
          },
          {
            "field": "uninitialized",
            "passed": true
          }
        ],
        "passed": true,
        "reasons": [],
        "reg": 5,
        "type": "NOT_INIT"
      },
      {
        "checks": [
          {
            "abstract": "NOT_INIT",
            "concrete_kind": "uninitialized",
            "field": "type",
            "passed": true
          },
          {
            "field": "uninitialized",
            "passed": true
          }
        ],
        "passed": true,
        "reasons": [],
        "reg": 6,
        "type": "NOT_INIT"
      },
      {
        "checks": [
          {
            "abstract": "NOT_INIT",
            "concrete_kind": "uninitialized",
            "field": "type",
            "passed": true
          },
          {
            "field": "uninitialized",
            "passed": true
          }
        ],
        "passed": true,
        "reasons": [],
        "reg": 7,
        "type": "NOT_INIT"
      },
      {
        "checks": [
          {
            "abstract": "NOT_INIT",
            "concrete_kind": "uninitialized",
            "field": "type",
            "passed": true
          },
          {
            "field": "uninitialized",
            "passed": true
          }
        ],
        "passed": true,
        "reasons": [],
        "reg": 8,
        "type": "NOT_INIT"
      },
      {
        "checks": [
          {
            "abstract": "NOT_INIT",
            "concrete_kind": "uninitialized",
            "field": "type",
            "passed": true
          },
          {
            "field": "uninitialized",
            "passed": true
          }
        ],
        "passed": true,
        "reasons": [],
        "reg": 9,
        "type": "NOT_INIT"
      },
      {
        "checks": [
          {
            "abstract": "PTR_TO_STACK",
            "concrete_kind": "ptr_to_stack",
            "field": "type",
            "passed": true
          },
          {
            "field": "ptr_kind",
            "passed": true
          },
          {
            "abstract": 0,
            "concrete": 0,
            "field": "offset",
            "passed": true
          },
          {
            "field": "var_off",
            "passed": true,
            "tnum": {
              "mask": 0,
              "value": 0
            }
          }
        ],
        "passed": true,
        "reasons": [],
        "reg": 10,
        "type": "PTR_TO_STACK"
      }
    ],
    "stack_slots": [
      {
        "checks": [
          {
            "field": "initialized",
            "passed": true
          },
          {
            "abstract": [
              0,
              0,
              0,
              0,
              0,
              0,
              0,
              0
            ],
            "field": "slot_type",
            "passed": true
          }
        ],
        "passed": true,
        "reasons": [],
        "slot": 0
      },
      {
        "checks": [
          {
            "field": "initialized",
            "passed": true
          },
          {
            "abstract": [
              0,
              0,
              0,
              0,
              0,
              0,
              0,
              0
            ],
            "field": "slot_type",
            "passed": true
          }
        ],
        "passed": true,
        "reasons": [],
        "slot": 1
      }
    ]
  },
  "passed": true,
  "reasons": [],
  "result": "SIGMA_A1_IN_DIRECT_GAMMA",
  "schema": "rac-direct-membership-v1",
  "unsupported_fields": []
}
