{
  "gates": [
    {
      "args": [
        "1",
        "1"
      ],
      "id": "g0",
      "op": "nand"
    },
    {
      "args": [
        "g0",
        "g0"
      ],
      "id": "g1",
      "op": "nand"
    },
    {
      "args": [
        "i2",
        "g1"
      ],
      "id": "g2",
      "op": "nand"
    },
    {
      "args": [
        "i0",
        "0"
      ],
      "id": "g3",
      "op": "nand"
    },
    {
      "args": [
        "i2",
        "g0"
      ],
      "id": "g4",
      "op": "nand"
    },
    {
      "args": [
        "g3",
        "g1"
      ],
      "id": "g5",
      "op": "nand"
    },
    {
      "args": [
        "i0",
        "g0"
      ],
      "id": "g6",
      "op": "nand"
    },
    {
      "args": [
        "1",
        "g0"
      ],
      "id": "g7",
      "op": "nand"
    },
    {
      "args": [
        "0",
        "g0"
      ],
      "id": "g8",
      "op": "nand"
    },
    {
      "args": [
        "g2",
        "g1"
      ],
      "id": "g9",
      "op": "nand"
    }
  ],
  "inputs": [
    "i0",
    "i1",
    "i2"
  ],
  "name": "rand_092",
  "outputs": [
    "g5",
    "i0"
  ]
}
